xls2json/__init__.py
xls2json/command_line.py
xls2json-0.1.2.dist-info/entry_points.txt
xls2json-0.1.2.dist-info/WHEEL
xls2json-0.1.2.dist-info/METADATA
xls2json-0.1.2.dist-info/RECORD
