Metadata-Version: 2.1
Name: xls2json
Version: 0.1.2
Summary: Convert XLS file to JSON.
Author: Reza Handzalah
Author-email: rezahandzalah@gmail.com
Requires-Python: >=3.6,<4.0
Classifier: Programming Language :: Python :: 3
Classifier: Programming Language :: Python :: 3.6
Classifier: Programming Language :: Python :: 3.7
Requires-Dist: xlrd (>=1.2,<2.0)
